invcalc/__init__.py
invcalc/inventory.py
invcalc/validator.py
invcalc-0.1.2.dist-info/METADATA
invcalc-0.1.2.dist-info/WHEEL
invcalc-0.1.2.dist-info/top_level.txt
invcalc-0.1.2.dist-info/RECORD
