Metadata-Version: 2.4
Name: invcalc
Version: 0.1.2
Summary: A Python library for inventory management and electronic component validation
Author-email: Gaddafi Adamu <gaddafiadamu400@gmail.com>
License-Expression: MIT
Requires-Python: >=3.8
